GetBourse/Iran.py
GetBourse/__init__.py
GetBourse-0.1.1.dist-info/METADATA
GetBourse-0.1.1.dist-info/WHEEL
GetBourse-0.1.1.dist-info/top_level.txt
GetBourse-0.1.1.dist-info/RECORD
