Metadata-Version: 2.1
Name: GetBourse
Version: 0.1.1
Summary: A Bourse Analysis Library  , Sponser: peyman6996
Author: Hossein Sayedmousavi
Author-email: Hossein.Sayyedmousavi@gmail.com
Requires-Dist: pandas
Requires-Dist: requests
Requires-Dist: bs4
Requires-Dist: setuptools
Requires-Dist: openpyxl
